pyuml2svg/__init__.py
pyuml2svg/cli.py
pyuml2svg/pyuml2svg.py
pyuml2svg/version.py
pyuml2svg/assets/script.js
pyuml2svg/assets/style.css
pyuml2svg-0.4.61.dist-info/licenses/LICENSE
pyuml2svg-0.4.61.dist-info/METADATA
pyuml2svg-0.4.61.dist-info/WHEEL
pyuml2svg-0.4.61.dist-info/entry_points.txt
pyuml2svg-0.4.61.dist-info/top_level.txt
pyuml2svg-0.4.61.dist-info/RECORD
