Metadata-Version: 2.4
Name: pyuml2svg
Version: 0.4.61
Summary: Pure Python UML class diagram generator that renders SVG without dependencies.
Author-email: Mikael Mölsä <mikael.molsa@pm.me>
License: MIT License
Keywords: uml,svg,diagram,python-uml,uml-renderer
Classifier: Programming Language :: Python :: 3
Classifier: License :: OSI Approved :: MIT License
Classifier: Environment :: Console
Classifier: Topic :: Software Development :: Documentation
Classifier: Topic :: Multimedia :: Graphics
Requires-Python: >=3.8
License-File: LICENSE
Dynamic: license-file
